hys_scraper/__init__.py
hys_scraper/__main__.py
hys_scraper/hys_scraper.py
hys_scraper-0.1.33.dist-info/LICENSE
hys_scraper-0.1.33.dist-info/METADATA
hys_scraper-0.1.33.dist-info/WHEEL
hys_scraper-0.1.33.dist-info/entry_points.txt
hys_scraper-0.1.33.dist-info/top_level.txt
hys_scraper-0.1.33.dist-info/RECORD
