Metadata-Version: 2.1
Name: hys-scraper
Version: 0.1.33
Summary: Scrape feedback and statistics from the European Commission's 'Have your Say' plattform.
Classifier: License :: OSI Approved :: GNU General Public License v3 (GPLv3)
Classifier: Programming Language :: Python
Classifier: Programming Language :: Python :: 3
Requires-Python: >=3.6
License-File: LICENSE
Requires-Dist: requests
Requires-Dist: pandas
